{"cameraMode":{"drawMode":0,"name":"Shaded","section":"Shading Mode"},"sceneLighting":true,"audioPlay":false,"sceneViewState":{"m_AlwaysRefresh":false,"showFog":true,"showSkybox":true,"showFlares":true,"showImageEffects":true,"showParticleSystems":true,"showVisualEffectGraphs":true,"m_FxEnabled":true},"in2DMode":false,"pivot":{"x":113.28890991210938,"y":8.727409362792969,"z":133.20022583007813},"rotation":{"x":-0.2583652138710022,"y":-0.0113402483984828,"z":0.002770013874396682,"w":-0.9660976529121399},"size":4.323943138122559,"orthographic":false}